mengjia/__init__.py
mengjia/mengjia.py
mengjia-0.1.4.dist-info/METADATA
mengjia-0.1.4.dist-info/WHEEL
mengjia-0.1.4.dist-info/top_level.txt
mengjia-0.1.4.dist-info/RECORD
