Metadata-Version: 2.4
Name: mengjia
Version: 0.1.4
Summary: A apikey generate method, the apikey will expire when current data  over input date
Author: zqk
Author-email: mengjia <your@email.com>
Classifier: Programming Language :: Python :: 3
Classifier: License :: OSI Approved :: MIT License
Requires-Python: >=3.7
Dynamic: author
